Metadata-Version: 2.1
Name: cmd-templateengine-python
Version: 1.0.0
Summary: Template Engine V1 - Create software component skeletons from templates
Home-page: https://bitbucket.org/entinco/eic-templateengine/src/master/cmd-templateengine-python
Author: Conceptual Vision Consulting LLC
Author-email: seroukhov@gmail.com
License: Commercial
Platform: any
Classifier: Intended Audience :: Developers
Classifier: License :: Other/Proprietary License
Classifier: Operating System :: OS Independent
Classifier: Programming Language :: Python
Classifier: Programming Language :: Python :: 3.12
Classifier: Programming Language :: Python :: 3.12
Classifier: Programming Language :: Python :: 3.12
Classifier: Programming Language :: Python :: 3.12
Classifier: Topic :: Software Development :: Libraries :: Python Modules
License-File: LICENSE
